{
  "max_lifetime": 10,
  "loop": false,
  "rate": 2,
  "count": 6,
  "emitter_settings": {
    "shape": {
      "shape": "veil:cube",
      "dimensions": [
        1.5,
        2.0,
        1.5
      ],
      "rotation": [
        0.0,
        0.0,
        0.0
      ],
      "from_surface": false
    },
    "particle_settings": {
      "particle_speed": 0.04,
      "random_speed": true,
      "base_particle_size": 0.36,
      "particle_size_variation": 0.06,
      "particle_lifetime": 16,
      "particle_lifetime_variation": 6,
      "initial_direction": [
        0.0,
        1.0,
        0.0
      ],
      "random_initial_direction": true,
      "random_initial_rotation": true,
      "random_size": true,
      "random_lifetime": true
    },
    "force_spawn": false
  },
  "particle_data": {
    "render_style": "veil:cube",
    "additive": true,
    "should_collide": false,
    "face_velocity": false,
    "velocity_stretch_factor": 0.0,
    "modules": [
      {
        "module": "veil:block"
      },
      {
        "module": "veil:color",
        "gradient": {
          "rgb_points": [
            {
              "percent": 0.0,
              "color": "#FFFFFF"
            },
            {
              "percent": 1.0,
              "color": "#FFFFFF"
            }
          ],
          "alpha_points": [
            {
              "percent": 0.0,
              "alpha": 0.0
            },
            {
              "percent": 0.25,
              "alpha": 0.9
            },
            {
              "percent": 0.7,
              "alpha": 0.75
            },
            {
              "percent": 1.0,
              "alpha": 0.0
            }
          ]
        },
        "interpolant": "q.agePercent"
      }
    ]
  }
}
